chromo/kinematics.py
chromo/util.py
chromo/constants.py
chromo/__init__.py
chromo/cli.py
chromo/common.py
chromo/decay_handler.py
chromo/writer.py
chromo/__main__.py
chromo/models/_sib21.cpython-313-darwin.so
chromo/models/_sib23c01.cpython-313-darwin.so
chromo/models/_sib23d_star.cpython-313-darwin.so
chromo/models/libpythia8.dylib
chromo/models/_dpmjet307.cpython-313-darwin.so
chromo/models/_qgs2_04.cpython-313-darwin.so
chromo/models/_sib23e_star.cpython-313-darwin.so
chromo/models/_phojet307.cpython-313-darwin.so
chromo/models/qgsjet.py
chromo/models/__init__.py
chromo/models/_eposlhcr.cpython-313-darwin.so
chromo/models/_urqmd34.cpython-313-darwin.so
chromo/models/dpmjetIII.py
chromo/models/_extra_models.py
chromo/models/sibyll.py
chromo/models/_qgs3.cpython-313-darwin.so
chromo/models/_sib23e.cpython-313-darwin.so
chromo/models/pythia6.py
chromo/models/epos.py
chromo/models/phojet.py
chromo/models/_pythia6.cpython-313-darwin.so
chromo/models/sophia.py
chromo/models/_qgs2_03.cpython-313-darwin.so
chromo/models/_sophia.cpython-313-darwin.so
chromo/models/_pythia8.cpython-313-darwin.so
chromo/models/_qgs01.cpython-313-darwin.so
chromo/models/_phojet191.cpython-313-darwin.so
chromo/models/pythia8.py
chromo/models/_dpmjet191.cpython-313-darwin.so
chromo/models/_sib23d.cpython-313-darwin.so
chromo/models/_eposlhc.cpython-313-darwin.so
chromo/models/_phojet193.cpython-313-darwin.so
chromo/models/urqmd.py
chromo/models/_dpmjet193.cpython-313-darwin.so
chromo/.dylibs/libstdc++.6.dylib
chromo/.dylibs/libgfortran.5.dylib
chromo/.dylibs/libquadmath.0.dylib
chromo/.dylibs/libgcc_s.1.1.dylib
chromo-0.10.0.dist-info/RECORD
chromo-0.10.0.dist-info/WHEEL
chromo-0.10.0.dist-info/entry_points.txt
chromo-0.10.0.dist-info/METADATA
