Metadata-Version: 2.1
Name: chromo
Version: 0.10.0
Summary: Hadronic Interaction Model interface in Python
Author-Email: Anatoli Fedynitch <afedynitch@gmail.com>, Hans Dembinski <hans.dembinski@gmail.com>, Anton Prosekin <ayprosekin@gmail.com>
Maintainer-Email: Anatoli Fedynitch <afedynitch@gmail.com>, Hans Dembinski <hans.dembinski@gmail.com>, Anton Prosekin <ayprosekin@gmail.com>
License: BSD 3-Clause License
Classifier: Development Status :: 4 - Beta
Classifier: Topic :: Scientific/Engineering :: Physics
Classifier: Intended Audience :: Science/Research
Classifier: Programming Language :: Python
Classifier: Programming Language :: Python :: 3
Classifier: License :: OSI Approved :: BSD License
Classifier: License :: OSI Approved :: GNU Library or Lesser General Public License (LGPL)
Project-URL: Homepage, https://github.com/impy-project/chromo
Project-URL: Download, https://pypi.python.org/pypi/chromo
Requires-Python: >=3.9
Requires-Dist: numpy
Requires-Dist: scipy
Requires-Dist: particle
Requires-Dist: rich
Provides-Extra: test
Requires-Dist: pytest; extra == "test"
Requires-Dist: pytest-benchmark; extra == "test"
Requires-Dist: pytest-xdist; extra == "test"
Requires-Dist: pyhepmc>=2.13.2; extra == "test"
Requires-Dist: uproot; extra == "test"
Requires-Dist: awkward; extra == "test"
Requires-Dist: pyyaml; extra == "test"
Requires-Dist: boost_histogram; extra == "test"
Requires-Dist: matplotlib; extra == "test"
Provides-Extra: examples
Requires-Dist: boost-histogram; extra == "examples"
Requires-Dist: matplotlib; extra == "examples"
Requires-Dist: tqdm; extra == "examples"
Requires-Dist: joblib; extra == "examples"
